cha-0.1.dist-info/metadata.json
cha-0.1.dist-info/RECORD
cha-0.1.dist-info/entry_points.txt
cha-0.1.dist-info/top_level.txt
cha-0.1.dist-info/WHEEL
cha-0.1.dist-info/DESCRIPTION.rst
cha-0.1.dist-info/METADATA
cc/words.db
cc/__main__.py
cc/c.py
cc/__init__.py
cc/create_db.py
