Metadata-Version: 2.0
Name: cha
Version: 0.1
Summary: UNKNOWN
Home-page: https://github.com/ubear/cha/
Author: chyoo
Author-email: chyoo1991@gmail.com
License: MIT
Keywords: sample cli tool to translate English to Chinese
Platform: linux
Classifier: Development Status :: 3 - Alpha
Classifier: Intended Audience :: Developers
Classifier: Topic :: Software Development :: Build Tools
Classifier: License :: OSI Approved :: MIT License
Classifier: Programming Language :: Python :: 2.7
Requires-Dist: requests (>=2.2.1)
Requires-Dist: BeautifulSoup (>=3.2.1)
Requires-Dist: sqlalchemy (>=1.0.14)
